semaforo.v
// Elaborado por: Daniel Octavio Marin Hernandez


// Se implementa un modulo con entradas y salidas para controlar un semaforo con tres estados: verde, amarillo y rojo.
module semaforo (
    input clk, reset,   

    input   verde,
            amarillo,
            rojo,            

    output reg rojo_out,
    output reg amarillo_out,
    output reg verde_out
);

    // Se declaran los estados del semaforo como parametros (Luz verde, luz amarilla, luz roja)
    parameter  EDO_VERDE    = 2'b00,
               EDO_AMARILLO = 2'b01,
               EDO_ROJO     = 2'b10;

    // Se declaran los registros para almacenar el estado actual y el siguiente estado del semaforo
    reg [1:0] current_state, next_state;

    // Se define la logica para actualizar el estado actual del semaforo en cada flanco positivo del reloj o cuando se active el reset
    always @(posedge clk or posedge reset) begin
        if (reset)
            current_state <= EDO_ROJO; // Por seguridad inicia en Rojo
        else
            current_state <= next_state; 
    end

    // Se define la logica  para determinar el siguiente estado del semaforo
    always @(*) 
    begin
        // Se inicializan las salidas en 0 por defecto
        rojo_out = 0;
        amarillo_out = 0;
        verde_out = 0;

        case (current_state)
            EDO_VERDE: 
            begin

                verde_out = 1; // Se enciende la salida del estado verde

                if (amarillo)
                    next_state = EDO_AMARILLO;   // De verde pasa a amarillo
                else
                    next_state = EDO_VERDE;     // Permanece en verde
            end
            EDO_AMARILLO: 
            begin
                amarillo_out = 1; // Se enciende la salida del estado amarillo

                if (rojo)
                    next_state = EDO_ROJO;     // De amarillo pasa a rojo
                else
                    next_state = EDO_AMARILLO; // Permanece en amarillo
            end
            EDO_ROJO: 
            begin
                rojo_out = 1; // Se enciende la salida del estado rojo

                if (verde)
                    next_state = EDO_VERDE;   // De rojo vuelve a verde
                else
                    next_state = EDO_ROJO;   // Permanece en rojo   
            end
            default: next_state = EDO_ROJO;
        endcase
    end

endmodule

semaforo_tb.v
// Elaborado por: Daniel Octavio Marin Hernandez

// Se implementa un modulo con entradas tipo reg y salidas tipo wire

module semaforo_tb();

reg clk, reset;

reg verde, 
    amarillo, 
    rojo;

wire rojo_out, 
     amarillo_out, 
     verde_out;

semaforo DUT (
    .clk(clk), 
    .reset(reset), 
    .verde(verde), 
    .amarillo(amarillo), 
    .rojo(rojo), 
    .rojo_out(rojo_out), 
    .amarillo_out(amarillo_out), 
    .verde_out(verde_out)
);

always #5 clk = ~clk; // Generador de reloj (cada 5 segundos alterna entre 0 y 1)

initial 
begin
    // Se inicializan las señales de entrada
    clk = 0;
    reset = 0;

    verde = 0;
    amarillo = 0;
    rojo = 0;

    #20;
    reset = 1; 
    #20
    reset = 0;
    
    #100;

    // Prueba de transición Verde a Amarillo
    verde = 1; 
    amarillo = 0; 
    rojo = 0;
    #30;
    verde = 0; 
    amarillo = 1; 
    rojo = 0;
    #10;
    // Prueba de transición Amarillo a Rojo
    verde = 0; 
    amarillo = 0; 
    rojo = 1;
    #45; 
    // Prueba de transición Rojo a Verde
    verde = 1; 
    amarillo = 0; 
    rojo = 0;
    #30;
    $finish;

end


initial
begin
    $monitor("Cambios de estado en el semaforo");
end

initial // Se genera un archivo VCD para visualizar las señales en GTKWave
begin
    $dumpfile("semaforo_tb.vcd"); 
    $dumpvars(0, semaforo_tb);
end
endmodule

semaforo_tb.vcd
$date
	Fri May 29 21:26:12 2026
$end
$version
	Icarus Verilog
$end
$timescale
	1s
$end
$scope module semaforo_tb $end
$var wire 1 ! verde_out $end
$var wire 1 " rojo_out $end
$var wire 1 # amarillo_out $end
$var reg 1 $ amarillo $end
$var reg 1 % clk $end
$var reg 1 & reset $end
$var reg 1 ' rojo $end
$var reg 1 ( verde $end
$scope module DUT $end
$var wire 1 $ amarillo $end
$var wire 1 % clk $end
$var wire 1 & reset $end
$var wire 1 ' rojo $end
$var wire 1 ( verde $end
$var parameter 2 ) EDO_AMARILLO $end
$var parameter 2 * EDO_ROJO $end
$var parameter 2 + EDO_VERDE $end
$var reg 1 # amarillo_out $end
$var reg 2 , current_state [1:0] $end
$var reg 2 - next_state [1:0] $end
$var reg 1 " rojo_out $end
$var reg 1 ! verde_out $end
$upscope $end
$upscope $end
$enddefinitions $end
$comment Show the parameter values. $end
$dumpall
b0 +
b10 *
b1 )
$end
#0
$dumpvars
b10 -
bx ,
0(
0'
0&
0%
0$
0#
0"
0!
$end
#5
1"
b10 ,
1%
#10
0%
#15
1%
#20
0%
1&
#25
1%
#30
0%
#35
1%
#40
0%
0&
#45
1%
#50
0%
#55
1%
#60
0%
#65
1%
#70
0%
#75
1%
#80
0%
#85
1%
#90
0%
#95
1%
#100
0%
#105
1%
#110
0%
#115
1%
#120
0%
#125
1%
#130
0%
#135
1%
#140
b0 -
1"
0%
1(
#145
1!
0"
b0 ,
1%
#150
0%
#155
1%
#160
0%
#165
1%
#170
b1 -
1!
0%
1$
0(
#175
1#
0!
b1 ,
1%
#180
b10 -
1#
0%
1'
0$
#185
1"
0#
b10 ,
1%
#190
0%
#195
1%
#200
0%
#205
1%
#210
0%
#215
1%
#220
0%
#225
1!
b0 ,
b0 -
0"
1%
0'
1(
